examples/__init__.py
tableschema_pandas/VERSION
tableschema_pandas/__init__.py
tableschema_pandas/mapper.py
tableschema_pandas/storage.py
tableschema_pandas-1.1.0.dist-info/LICENSE.md
tableschema_pandas-1.1.0.dist-info/METADATA
tableschema_pandas-1.1.0.dist-info/WHEEL
tableschema_pandas-1.1.0.dist-info/top_level.txt
tableschema_pandas-1.1.0.dist-info/RECORD
