Metadata-Version: 2.1
Name: tableschema-pandas
Version: 1.1.0
Summary: Generate Pandas data frames, load and extract data, based on JSON Table Schema descriptors.
Home-page: https://github.com/frictionlessdata/tableschema-pandas-py
Author: Open Knowledge Foundation
Author-email: info@okfn.org
License: LGPLv3+
Keywords: frictionless data,datapackage,pandas
Platform: UNKNOWN
Classifier: Development Status :: 4 - Beta
Classifier: Intended Audience :: Developers
Classifier: Intended Audience :: Science/Research
Classifier: License :: OSI Approved :: GNU Lesser General Public License v3 or later (LGPLv3+)
Classifier: Operating System :: OS Independent
Classifier: Programming Language :: Python :: 2
Classifier: Programming Language :: Python :: 2.7
Classifier: Programming Language :: Python :: 3
Classifier: Programming Language :: Python :: 3.4
Classifier: Programming Language :: Python :: 3.5
Classifier: Topic :: Scientific/Engineering :: Information Analysis
Classifier: Topic :: Software Development :: Libraries :: Python Modules
Requires-Dist: six (>=1.9)
Requires-Dist: pandas (>=0.18)
Requires-Dist: tabulator (>=1.0)
Requires-Dist: tableschema (>=1.1)
Requires-Dist: isodate (>=0.6)
Provides-Extra: develop
Requires-Dist: mock ; extra == 'develop'
Requires-Dist: pylama ; extra == 'develop'
Requires-Dist: pytest ; extra == 'develop'
Requires-Dist: pytest-cov ; extra == 'develop'
Requires-Dist: tox ; extra == 'develop'
